Metadata-Version: 2.1
Name: django-easy-docs-bs5
Version: 2.0.0
Summary: A simple documentation app for Django, using Bootstrap 5.
Home-page: https://github.com/sploro-git/django-easy-docs-bs5
Author: Ivan Pajares
Author-email: ivan.pajares@sploro.eu
License: MIT
Download-URL: https://pypi.org/project/django-easy-docs-bs5/
Keywords: django,documentation,docs,easy,simple
Platform: UNKNOWN
Classifier: Development Status :: 5 - Production/Stable
Classifier: Environment :: Web Environment
Classifier: Framework :: Django
Classifier: Framework :: Django :: 3.2
Classifier: Intended Audience :: Developers
Classifier: License :: OSI Approved :: MIT License
Classifier: Operating System :: OS Independent
Classifier: Programming Language :: Python
Classifier: Programming Language :: Python :: 3
Classifier: Programming Language :: Python :: 3.9
Classifier: Topic :: Internet :: WWW/HTTP
Classifier: Topic :: Internet :: WWW/HTTP :: Dynamic Content
License-File: LICENSE.txt
Requires-Dist: Django>=4.0
Requires-Dist: django-markdownx>=4.0.7
Requires-Dist: django-simple-history>=3.4.0
Requires-Dist: markdown>=3.5.1
Requires-Dist: django-htmx>=1.17.2
